cflib/__init__.py
cflib/cf.py
cflib/fasta.py
cflib/gp.py
cflib/main.py
cflib/seqbase.py
cflib/vcf.py
cflib_pomo-1.3.0.0.data/scripts/CountsToFasta.py
cflib_pomo-1.3.0.0.data/scripts/FastaToCounts.py
cflib_pomo-1.3.0.0.data/scripts/FastaToVCF.py
cflib_pomo-1.3.0.0.data/scripts/FastaVCFToCounts.py
cflib_pomo-1.3.0.0.data/scripts/FilterMSA.py
cflib_pomo-1.3.0.0.data/scripts/GPToCounts.py
cflib_pomo-1.3.0.0.data/scripts/MSAToCounts.py
cflib_pomo-1.3.0.0.dist-info/LICENSE.TXT
cflib_pomo-1.3.0.0.dist-info/METADATA
cflib_pomo-1.3.0.0.dist-info/WHEEL
cflib_pomo-1.3.0.0.dist-info/top_level.txt
cflib_pomo-1.3.0.0.dist-info/RECORD
