Metadata-Version: 2.1
Name: cflib-pomo
Version: 1.3.0.0
Summary: Counts file library and conversion scripts.
Home-page: https://github.com/pomo-dev/cflib
Author: Dominik Schrempf
Author-email: dominik.schrempf@gmail.com
License: MIT
Keywords: counts fasta files multi sequence alignments
Platform: UNKNOWN
Classifier: Intended Audience :: Science/Research
Requires-Dist: scipy
Requires-Dist: numpy
Requires-Dist: pysam
